{
    "keep": {
        "days": true,
        "amount": 1
    },
    "auditLog": "src/logs/.570213950cda6750dd12f763d58076ac69a1aca6-audit.json",
    "files": [
        {
            "date": 1732755123952,
            "name": "src/logs/2024-11-28.info.log",
            "hash": "45e5e610cbaa16a925ccf619e190b3c8e3819723b36bb3764fd19eb335e23631"
        },
        {
            "date": 1732813216209,
            "name": "src/logs/2024-11-29.info.log",
            "hash": "5f413453289c72a94e9b2a46345ecaf7b08ffee9459f39515b1e0763327b3604"
        }
    ],
    "hashType": "sha256"
}